Workbook

Sheet Sheet1
A1: Campaign Name | B1: Funnel Stage | C1: Channel | D1: Visitors/Leads | E1: Conversions | F1: Conversion Rate (%) | G1: Cost ($) | H1: Revenue ($) | I1: Profit
A2: Campaign 1 | B2: Awareness | C2: Facebook Ads | D2: 5000 | E2: 450 | F2: 9 | G2: 800 | H2: 0 | I2: =H2-G2 -> -800
A3: Campaign 2 | B3: Awareness | C3: Google Ads | D3: 6200 | E3: 620 | F3: 10 | G3: 1000 | H3: 0 | I3: =H3-G3 -> -1000
A4: Campaign 3 | B4: Awareness | C4: Instagram Ads | D4: 4100 | E4: 320 | F4: 7.8 | G4: 650 | H4: 0 | I4: =H4-G4 -> -650
A5: Campaign 4 | B5: Interest | C5: Website Organic | D5: 3500 | E5: 700 | F5: 20 | G5: 300 | H5: 0 | I5: =H5-G5 -> -300
A6: Campaign 5 | B6: Interest | C6: Email Marketing | D6: 2800 | E6: 840 | F6: 30 | G6: 200 | H6: 0 | I6: =H6-G6 -> -200
A7: Campaign 6 | B7: Interest | C7: LinkedIn Ads | D7: 2600 | E7: 390 | F7: 15 | G7: 500 | H7: 0 | I7: =H7-G7 -> -500
A8: Campaign 7 | B8: Consideration | C8: Website Retargeting | D8: 2200 | E8: 550 | F8: 25 | G8: 450 | H8: 0 | I8: =H8-G8 -> -450
A9: Campaign 8 | B9: Consideration | C9: Email Nurturing | D9: 1900 | E9: 570 | F9: 30 | G9: 180 | H9: 0 | I9: =H9-G9 -> -180
A10: Campaign 9 | B10: Consideration | C10: YouTube Ads | D10: 3000 | E10: 360 | F10: 12 | G10: 700 | H10: 0 | I10: =H10-G10 -> -700
A11: Campaign 10 | B11: Consideration | C11: Referral Traffic | D11: 1700 | E11: 425 | F11: 25 | G11: 150 | H11: 0 | I11: =H11-G11 -> -150
A12: Campaign 11 | B12: Intent | C12: Free Trial Signup | D12: 1200 | E12: 360 | F12: 30 | G12: 0 | H12: 0 | I12: =H12-G12 -> 0
A13: Campaign 12 | B13: Intent | C13: Demo Request | D13: 900 | E13: 315 | F13: 35 | G13: 0 | H13: 0 | I13: =H13-G13 -> 0
... A26: Campaign 25 | B26: Retention | C26: Renewal Campaign | D26: 140 | E26: 98 | F26: 70 | G26: 120 | H26: 4900 | I26: =H26-G26 -> 4780

Sheet Cost Revenue Summary
A1: Funnel Stage | B1: Total Cost | C1: Total Revenue | D1: Profit
A2: Awareness | B2: =SUMIF(Sheet1!B:B,A2,Sheet1!G:G) -> 2450 | C2: =SUMIF(Sheet1!B:B,A2,Sheet1!H:H) -> 0 | D2: =C2-B2 -> -2450
A3: Interest | B3: =SUMIF(Sheet1!B:B,A3,Sheet1!G:G) -> 1000 | C3: =SUMIF(Sheet1!B:B,A3,Sheet1!H:H) -> 0 | D3: =C3-B3 -> -1000
A4: Consideration | B4: =SUMIF(Sheet1!B:B,A4,Sheet1!G:G) -> 1480 | C4: =SUMIF(Sheet1!B:B,A4,Sheet1!H:H) -> 0 | D4: =C4-B4 -> -1480
A5: Intent | B5: =SUMIF(Sheet1!B:B,A5,Sheet1!G:G) -> 500 | C5: =SUMIF(Sheet1!B:B,A5,Sheet1!H:H) -> 0 | D5: =C5-B5 -> -500
A6: Evaluation | B6: =SUMIF(Sheet1!B:B,A6,Sheet1!G:G) -> 0 | C6: =SUMIF(Sheet1!B:B,A6,Sheet1!H:H) -> 0 | D6: =C6-B6 -> 0
A7: Purchase | B7: =SUMIF(Sheet1!B:B,A7,Sheet1!G:G) -> 0 | C7: =SUMIF(Sheet1!B:B,A7,Sheet1!H:H) -> 22500 | D7: =C7-B7 -> 22500
A8: Retention | B8: =SUMIF(Sheet1!B:B,A8,Sheet1!G:G) -> 220 | C8: =SUMIF(Sheet1!B:B,A8,Sheet1!H:H) -> 8100 | D8: =C8-B8 -> 7880

Sheet Funnel Summary
A1: Funnel Stage | B1: Total Visitors | C1: Total Conversions | D1: Conversion Rate(%)
A2: Awareness | B2: =SUMIF(Sheet1!B:B,A2,Sheet1!D:D) -> 15300 | C2: =SUMIF(Sheet1!B:B,A2,Sheet1!E:E) -> 1390 | D2: =C2/B2*100 -> 9.0849673
A3: Interest | B3: =SUMIF(Sheet1!B:B,A3,Sheet1!D:D) -> 8900 | C3: =SUMIF(Sheet1!B:B,A3,Sheet1!E:E) -> 1930 | D3: =C3/B3*100 -> 21.685393
A4: Consideration | B4: =SUMIF(Sheet1!B:B,A4,Sheet1!D:D) -> 8800 | C4: =SUMIF(Sheet1!B:B,A4,Sheet1!E:E) -> 1905 | D4: =C4/B4*100 -> 21.647727
A5: Intent | B5: =SUMIF(Sheet1!B:B,A5,Sheet1!D:D) -> 4700 | C5: =SUMIF(Sheet1!B:B,A5,Sheet1!E:E) -> 1400 | D5: =C5/B5*100 -> 29.787234
A6: Evaluation | B6: =SUMIF(Sheet1!B:B,A6,Sheet1!D:D) -> 1600 | C6: =SUMIF(Sheet1!B:B,A6,Sheet1!E:E) -> 610 | D6: =C6/B6*100 -> 38.125
A7: Purchase | B7: =SUMIF(Sheet1!B:B,A7,Sheet1!D:D) -> 630 | C7: =SUMIF(Sheet1!B:B,A7,Sheet1!E:E) -> 630 | D7: =C7/B7*100 -> 100
A8: Retention | B8: =SUMIF(Sheet1!B:B,A8,Sheet1!D:D) -> 300 | C8: =SUMIF(Sheet1!B:B,A8,Sheet1!E:E) -> 162 | D8: =C8/B8*100 -> 54

Sheet performance Analysis
A1: Channel | B1: Total Visitors | C1: Total Conversions | D1: Conversion Rate(%)
A2: Facebook Ads | B2: =SUMIF(Sheet1!C:C,A2,Sheet1!D:D) -> 5000 | C2: =SUMIF(Sheet1!C:C,A2,Sheet1!E:E) -> 450 | D2: =C2/B2*100 -> 9
A3: Google Ads | B3: =SUMIF(Sheet1!C:C,A3,Sheet1!D:D) -> 6200 | C3: =SUMIF(Sheet1!C:C,A3,Sheet1!E:E) -> 620 | D3: =C3/B3*100 -> 10
A4: Instagram Ads | B4: =SUMIF(Sheet1!C:C,A4,Sheet1!D:D) -> 4100 | C4: =SUMIF(Sheet1!C:C,A4,Sheet1!E:E) -> 320 | D4: =C4/B4*100 -> 7.804878
A5: Email Marketing | B5: =SUMIF(Sheet1!C:C,A5,Sheet1!D:D) -> 2800 | C5: =SUMIF(Sheet1!C:C,A5,Sheet1!E:E) -> 840 | D5: =C5/B5*100 -> 30
A6: Website Organic | B6: =SUMIF(Sheet1!C:C,A6,Sheet1!D:D) -> 3500 | C6: =SUMIF(Sheet1!C:C,A6,Sheet1!E:E) -> 700 | D6: =C6/B6*100 -> 20

Sheet Sheet5
A1: key insights:
A2: Awareness stage has the highest traffic but the lowest conversion rate.
A3: Conversion efficiency improves as users move towards Purchase and Retention.
A4: Google Ads and Email Marketing channels perform better than social media platforms.
A5: Maximum drop-off occurs between Consideration and Intent stages.
A6: Retention stage generates higher revenue with comparatively lower cost.
